agiflow_eval/.DS_Store
agiflow_eval/__init__.py
agiflow_eval/aggregators/__init__.py
agiflow_eval/aggregators/metadata.py
agiflow_eval/config/__init__.py
agiflow_eval/config/environment_vars.py
agiflow_eval/constants/__init__.py
agiflow_eval/llm/.DS_Store
agiflow_eval/llm/__init__.py
agiflow_eval/llm/base.py
agiflow_eval/llm/lite_llm.py
agiflow_eval/metrics/__init__.py
agiflow_eval/metrics/answer_relevancy/__init__.py
agiflow_eval/metrics/answer_relevancy/evaluation.py
agiflow_eval/metrics/answer_relevancy/template.py
agiflow_eval/metrics/base_metric.py
agiflow_eval/metrics/bias/__init__.py
agiflow_eval/metrics/bias/evaluation.py
agiflow_eval/metrics/bias/template.py
agiflow_eval/metrics/contextual_relevancy/__init__.py
agiflow_eval/metrics/contextual_relevancy/evaluation.py
agiflow_eval/metrics/contextual_relevancy/template.py
agiflow_eval/metrics/faithfulness/__init__.py
agiflow_eval/metrics/faithfulness/evaluation.py
agiflow_eval/metrics/faithfulness/template.py
agiflow_eval/metrics/hallucination/__init__.py
agiflow_eval/metrics/hallucination/evaluation.py
agiflow_eval/metrics/hallucination/template.py
agiflow_eval/metrics/indicator.py
agiflow_eval/metrics/toxicity/__init__.py
agiflow_eval/metrics/toxicity/evaluation.py
agiflow_eval/metrics/toxicity/template.py
agiflow_eval/telemetry.py
agiflow_eval/test_case/__init__.py
agiflow_eval/test_case/conversational_test_case.py
agiflow_eval/test_case/llm_test_case.py
agiflow_eval/utils/__init__.py
agiflow_eval/utils/coroutine.py
agiflow_eval/utils/decorators.py
agiflow_eval/utils/env.py
agiflow_eval/utils/file.py
agiflow_eval/utils/gpu.py
agiflow_eval/utils/math.py
agiflow_eval/utils/object.py
agiflow_eval/utils/text.py
agiflow_eval/version.py
agiflow_eval-0.0.2.dist-info/METADATA
agiflow_eval-0.0.2.dist-info/WHEEL
agiflow_eval-0.0.2.dist-info/RECORD
