Metadata-Version: 2.1
Name: agiflow-eval
Version: 0.0.2
Summary: Agiflow (EVAL) for Python
Home-page: https://github.com/AgiFlow/agiflow-sdks
License: MIT
Author: Vuong Ngo
Author-email: vuongngo.pd@gmail.com
Requires-Python: >=3.9,<4
Classifier: License :: OSI Approved :: MIT License
Classifier: Programming Language :: Python :: 3
Classifier: Programming Language :: Python :: 3.9
Classifier: Programming Language :: Python :: 3.10
Classifier: Programming Language :: Python :: 3.11
Classifier: Programming Language :: Python :: 3.12
Requires-Dist: deprecated (>=1.2.14,<2.0.0)
Requires-Dist: jinja2 (>=3.1.4,<4.0.0)
Requires-Dist: litellm (>=1.40.15,<2.0.0)
Requires-Dist: posthog (>=3.0.2,<4.0.0)
Requires-Dist: pydantic (>=2.5.3,<3.0.0)
Requires-Dist: rich (==13.7.1)
Project-URL: Documentation, https://docs.agiflow.io/python-agiflow-eval
Project-URL: Repository, https://github.com/AgiFlow/agiflow-sdks
